README.rst
setup.py
Tumulus.egg-info/PKG-INFO
Tumulus.egg-info/SOURCES.txt
Tumulus.egg-info/dependency_links.txt
Tumulus.egg-info/requires.txt
Tumulus.egg-info/top_level.txt
tumulus/__init__.py
tumulus/element.py
tumulus/embed.py
tumulus/formulas.py
tumulus/tag.py
tumulus/tags.py
tumulus/templating.py
tumulus/lib/__init__.py
tumulus/plugins/__init__.py