Metadata-Version: 1.1
Name: Tumulus
Version: 0.1.5
Summary: Python HTML Generator for Recyclable Web Elements
Home-page: https://github.com/oksome/Tumulus/
Author: OKso.me
Author-email: @okso.me
License: AGPLv3
Keywords: html generator template templating engine
Platform: UNKNOWN
Classifier: Development Status :: 3 - Alpha
Classifier: Environment :: Web Environment
Classifier: Programming Language :: Python :: 3
Classifier: Operating System :: POSIX
Classifier: Operating System :: POSIX :: Linux
Classifier: Operating System :: MacOS :: MacOS X
Classifier: Intended Audience :: Developers
Classifier: License :: OSI Approved :: GNU Affero General Public License v3
Classifier: Topic :: Internet :: WWW/HTTP :: Dynamic Content
Classifier: Topic :: Software Development :: Code Generators
Classifier: Topic :: Software Development :: Libraries :: Python Modules
Classifier: Topic :: Text Processing :: Markup :: HTML 
